text_games/__init__.py
text_games/hangman.py
text_games/number_guesser.py
text_games/riddle_game.py
text_games/rock_paper_scissor.py
text_games/snake_game.py
text_games/tic_tac_toe.py
text_games/word_scrambler.py
text_games-0.2.3.dist-info/LICENSE
text_games-0.2.3.dist-info/METADATA
text_games-0.2.3.dist-info/WHEEL
text_games-0.2.3.dist-info/top_level.txt
text_games-0.2.3.dist-info/RECORD
