Metadata-Version: 2.1
Name: text_games
Version: 0.2.3
Summary: A collection of text-based games in Python.
Home-page: https://github.com/Sriganth-byte/Python_Text_Games
Author: Sriganth
Author-email: sriganthperiyannan@example.com
License: MIT
Project-URL: Bug Tracker, https://github.com/Sriganth-byte/Python_Text_Games/issues
Project-URL: Source Code, https://github.com/Sriganth-byte/Python_Text_Games
Keywords: games text-based python snake hangman tic-tac-toe puzzles
Classifier: Development Status :: 4 - Beta
Classifier: Intended Audience :: Developers
Classifier: Topic :: Games/Entertainment :: Puzzle Games
Classifier: License :: OSI Approved :: MIT License
Classifier: Programming Language :: Python :: 3
Classifier: Programming Language :: Python :: 3.9
Classifier: Programming Language :: Python :: 3.10
Classifier: Programming Language :: Python :: 3.11
Classifier: Programming Language :: Python :: Implementation :: CPython
Classifier: Programming Language :: Python :: Implementation :: PyPy
Requires-Python: >=3.7
License-File: LICENSE
Requires-Dist: pygame
Requires-Dist: tk
